README.rst
setup.py
ceiclient/__init__.py
ceiclient/cli.py
ceiclient/client.py
ceiclient/commands.py
ceiclient/common.py
ceiclient/connection.py
ceiclient/exception.py
ceiclient.egg-info/PKG-INFO
ceiclient.egg-info/SOURCES.txt
ceiclient.egg-info/dependency_links.txt
ceiclient.egg-info/entry_points.txt
ceiclient.egg-info/requires.txt
ceiclient.egg-info/top_level.txt