Metadata-Version: 1.0
Name: ceiclient
Version: 0.2.0
Summary: Client tools for the OOI Common Execution Infrastructure
Home-page: http://github.com/nimbusproject/ceiclient
Author: Nimbus team
Author-email: nimbus@mcs.anl.gov
License: Apache 2.0
Download-URL: http://www.nimbusproject.org/downloads/ceiclient-0.2.0.tar.gz
Platform: UNKNOWN
